<xit:registries xmlns:xit="http://www.x.org/xorg-integration-testing">
  <xit:registry name="xorg-upstream">
    <xit:meta>
      <xit:date>2012-12-18</xit:date>
      <xit:moduleversion name="xserver" type="git" repo="git://git.freedesktop.org/git/xorg/xserver">bd91b05b631f13afd1f7a9d6cbc4f0c5408b523a</xit:moduleversion>
    </xit:meta>
    <xit:testsuite name="BarrierConflictingDirections">
      <xit:testcase name="InvalidConflictingDirectionsBarrier/0" success="true"/>
      <xit:testcase name="InvalidConflictingDirectionsBarrier/1" success="true"/>
      <xit:testcase name="InvalidConflictingDirectionsBarrier/2" success="true"/>
      <xit:testcase name="InvalidConflictingDirectionsBarrier/3" success="true"/>
      <xit:testcase name="InvalidConflictingDirectionsBarrier/4" success="true"/>
      <xit:testcase name="InvalidConflictingDirectionsBarrier/5" success="true"/>
      <xit:testcase name="InvalidConflictingDirectionsBarrier/6" success="true"/>
      <xit:testcase name="InvalidConflictingDirectionsBarrier/7" success="true"/>
      <xit:testcase name="InvalidConflictingDirectionsBarrier/8" success="true"/>
    </xit:testsuite>
    <xit:testsuite name="BarrierConstrained">
      <xit:testcase name="HoritzontalBarrierNegativeYBlocksMotion" success="true"/>
      <xit:testcase name="HoritzontalBarrierPositiveYBlocksMotion" success="true"/>
      <xit:testcase name="HorizontalBarrierBothDirectionsYBlocksNoMotion" success="true"/>
      <xit:testcase name="HorizontalBarrierNoDirectionBlocksMotion" success="true"/>
      <xit:testcase name="VerticalBarrierBothDirectionsXBlocksNoMotion" success="true"/>
      <xit:testcase name="VerticalBarrierNegativeXBlocksMotion" success="true"/>
      <xit:testcase name="VerticalBarrierNoDirectionBlocksMotion" success="true"/>
      <xit:testcase name="VerticalBarrierPositiveXBlocksMotion" success="true"/>
    </xit:testsuite>
    <xit:testsuite name="BarrierDevices">
      <xit:testcase name="BarrierBlocksCorrectDevices" success="true"/>
    </xit:testsuite>
    <xit:testsuite name="BarrierNonZeroArea">
      <xit:testcase name="InvalidNonZeroAreaBarrier/0" success="true"/>
      <xit:testcase name="InvalidNonZeroAreaBarrier/1" success="true"/>
      <xit:testcase name="InvalidNonZeroAreaBarrier/2" success="true"/>
      <xit:testcase name="InvalidNonZeroAreaBarrier/3" success="true"/>
      <xit:testcase name="InvalidNonZeroAreaBarrier/4" success="true"/>
      <xit:testcase name="InvalidNonZeroAreaBarrier/5" success="true"/>
      <xit:testcase name="InvalidNonZeroAreaBarrier/6" success="true"/>
    </xit:testsuite>
    <xit:testsuite name="BarrierSimpleTest">
      <xit:testcase name="CreateAndDestroyBarrier" success="true"/>
      <xit:testcase name="DestroyInvalidBarrier" success="true"/>
      <xit:testcase name="InvalidDeviceCausesBadDevice" success="true"/>
    </xit:testsuite>
    <xit:testsuite name="BarrierZeroLength">
      <xit:testcase name="InvalidZeroLengthBarrier/0" success="true"/>
      <xit:testcase name="InvalidZeroLengthBarrier/1" success="true"/>
      <xit:testcase name="InvalidZeroLengthBarrier/2" success="true"/>
      <xit:testcase name="InvalidZeroLengthBarrier/3" success="true"/>
      <xit:testcase name="InvalidZeroLengthBarrier/4" success="true"/>
      <xit:testcase name="InvalidZeroLengthBarrier/5" success="true"/>
      <xit:testcase name="InvalidZeroLengthBarrier/6" success="true"/>
    </xit:testsuite>
    <xit:testsuite name="EventQueueTest">
      <xit:testcase name="mieqOverflow" success="true"/>
    </xit:testsuite>
    <xit:testsuite name="MiscServerTest">
      <xit:testcase name="DoubleSegfault" success="true"/>
    </xit:testsuite>
    <xit:testsuite name="PointerGrabTest">
      <xit:testcase name="GrabDisabledDevices" success="true"/>
      <xit:testcase name="ImplicitGrabRawEvents" success="false"/>
    </xit:testsuite>
    <xit:testsuite name="PointerGrabTypeTest">
      <xit:testcase name="DifferentGrabTypesProhibited/0" success="true">
        <xit:bug type="bugzilla">https://bugs.freedesktop.org/show_bug.cgi?id=58255</xit:bug>
      </xit:testcase>
      <xit:testcase name="DifferentGrabTypesProhibited/1" success="true">
        <xit:bug type="bugzilla">https://bugs.freedesktop.org/show_bug.cgi?id=58255</xit:bug>
      </xit:testcase>
      <xit:testcase name="DifferentGrabTypesProhibited/2" success="true">
        <xit:bug type="bugzilla">https://bugs.freedesktop.org/show_bug.cgi?id=58255</xit:bug>
        <xit:fix type="git" repo="git://git.freedesktop.org/git/xorg/xserver">dd3242c87a0a58cba055eb99c0c3fcf03153e4b8</xit:fix>
      </xit:testcase>
      <xit:testcase name="DifferentGrabTypesProhibited/3" success="true">
        <xit:bug type="bugzilla">https://bugs.freedesktop.org/show_bug.cgi?id=58255</xit:bug>
      </xit:testcase>
      <xit:testcase name="DifferentGrabTypesProhibited/4" success="true">
        <xit:bug type="bugzilla">https://bugs.freedesktop.org/show_bug.cgi?id=58255</xit:bug>
      </xit:testcase>
      <xit:testcase name="DifferentGrabTypesProhibited/5" success="true">
        <xit:bug type="bugzilla">https://bugs.freedesktop.org/show_bug.cgi?id=58255</xit:bug>
        <xit:fix type="git" repo="git://git.freedesktop.org/git/xorg/xserver">dd3242c87a0a58cba055eb99c0c3fcf03153e4b8</xit:fix>
      </xit:testcase>
      <xit:testcase name="DifferentGrabTypesProhibited/6" success="true">
        <xit:bug type="bugzilla">https://bugs.freedesktop.org/show_bug.cgi?id=58255</xit:bug>
        <xit:fix type="git" repo="git://git.freedesktop.org/git/xorg/xserver">dd3242c87a0a58cba055eb99c0c3fcf03153e4b8</xit:fix>
      </xit:testcase>
      <xit:testcase name="DifferentGrabTypesProhibited/7" success="true">
        <xit:bug type="bugzilla">https://bugs.freedesktop.org/show_bug.cgi?id=58255</xit:bug>
        <xit:fix type="git" repo="git://git.freedesktop.org/git/xorg/xserver">dd3242c87a0a58cba055eb99c0c3fcf03153e4b8</xit:fix>
      </xit:testcase>
      <xit:testcase name="DifferentGrabTypesProhibited/8" success="true">
        <xit:bug type="bugzilla">https://bugs.freedesktop.org/show_bug.cgi?id=58255</xit:bug>
      </xit:testcase>
    </xit:testsuite>
    <xit:testsuite name="PointerMotionTest">
      <xit:testcase name="NoSubpixelCoreEvents" success="false">
        <xit:bug type="bugzilla">https://bugs.freedesktop.org/show_bug.cgi?id=57383</xit:bug>
      </xit:testcase>
    </xit:testsuite>
    <xit:testsuite name="ScreenSaverTest">
      <xit:testcase name="ScreenSaverActivateDeactivate" success="true">
        <xit:bug type="bugzilla">https://bugs.freedesktop.org/show_bug.cgi?id=56649</xit:bug>
        <xit:fix type="git" repo="git://git.freedesktop.org/git/xorg/xserver">2dc6d9228456cbc274a1fcea478258e5ae4dc629</xit:fix>
      </xit:testcase>
    </xit:testsuite>
    <xit:testsuite name="TouchDeviceChangeTest">
      <xit:testcase name="DeviceChangedEventPointerToTouchSwitch" success="true"/>
      <xit:testcase name="DeviceChangedEventTouchToPointerSwitch" success="true"/>
      <xit:testcase name="NoCursorJumpsOnTouchToPointerSwitch" success="true">
        <xit:bug type="bugzilla">https://bugs.freedesktop.org/show_bug.cgi?id=49347</xit:bug>
        <xit:fix type="git" repo="git://git.freedesktop.org/git/xorg/xserver">3b9f1c701787965246638c1a6fd99fb2b6078114</xit:fix>
      </xit:testcase>
    </xit:testsuite>
    <xit:testsuite name="TouchDeviceTest">
      <xit:testcase name="DisableDeviceEndTouches" success="true"/>
    </xit:testsuite>
    <xit:testsuite name="TouchEventHistoryTest">
      <xit:testcase name="EventHistoryReplay/0" success="true">
        <xit:bug type="bugzilla">https://bugs.freedesktop.org/show_bug.cgi?id=55477</xit:bug>
        <xit:fix type="git" repo="git://git.freedesktop.org/git/xorg/xserver">ce6b6529290f7d42717aad3fd8a83aaaaf8962de</xit:fix>
      </xit:testcase>
      <xit:testcase name="EventHistoryReplay/1" success="true">
        <xit:bug type="bugzilla">https://bugs.freedesktop.org/show_bug.cgi?id=55477</xit:bug>
        <xit:fix type="git" repo="git://git.freedesktop.org/git/xorg/xserver">ce6b6529290f7d42717aad3fd8a83aaaaf8962de</xit:fix>
      </xit:testcase>
      <xit:testcase name="EventHistoryReplay/10" success="true">
        <xit:bug type="bugzilla">https://bugs.freedesktop.org/show_bug.cgi?id=55477</xit:bug>
        <xit:fix type="git" repo="git://git.freedesktop.org/git/xorg/xserver">ce6b6529290f7d42717aad3fd8a83aaaaf8962de</xit:fix>
      </xit:testcase>
      <xit:testcase name="EventHistoryReplay/11" success="true">
        <xit:bug type="bugzilla">https://bugs.freedesktop.org/show_bug.cgi?id=55477</xit:bug>
        <xit:fix type="git" repo="git://git.freedesktop.org/git/xorg/xserver">ce6b6529290f7d42717aad3fd8a83aaaaf8962de</xit:fix>
      </xit:testcase>
      <xit:testcase name="EventHistoryReplay/12" success="true">
        <xit:bug type="bugzilla">https://bugs.freedesktop.org/show_bug.cgi?id=55477</xit:bug>
        <xit:fix type="git" repo="git://git.freedesktop.org/git/xorg/xserver">ce6b6529290f7d42717aad3fd8a83aaaaf8962de</xit:fix>
      </xit:testcase>
      <xit:testcase name="EventHistoryReplay/13" success="true">
        <xit:bug type="bugzilla">https://bugs.freedesktop.org/show_bug.cgi?id=55477</xit:bug>
        <xit:fix type="git" repo="git://git.freedesktop.org/git/xorg/xserver">ce6b6529290f7d42717aad3fd8a83aaaaf8962de</xit:fix>
      </xit:testcase>
      <xit:testcase name="EventHistoryReplay/14" success="true">
        <xit:bug type="bugzilla">https://bugs.freedesktop.org/show_bug.cgi?id=55477</xit:bug>
        <xit:fix type="git" repo="git://git.freedesktop.org/git/xorg/xserver">ce6b6529290f7d42717aad3fd8a83aaaaf8962de</xit:fix>
      </xit:testcase>
      <xit:testcase name="EventHistoryReplay/15" success="true">
        <xit:bug type="bugzilla">https://bugs.freedesktop.org/show_bug.cgi?id=55477</xit:bug>
        <xit:fix type="git" repo="git://git.freedesktop.org/git/xorg/xserver">ce6b6529290f7d42717aad3fd8a83aaaaf8962de</xit:fix>
      </xit:testcase>
      <xit:testcase name="EventHistoryReplay/16" success="true">
        <xit:bug type="bugzilla">https://bugs.freedesktop.org/show_bug.cgi?id=55477</xit:bug>
        <xit:fix type="git" repo="git://git.freedesktop.org/git/xorg/xserver">ce6b6529290f7d42717aad3fd8a83aaaaf8962de</xit:fix>
      </xit:testcase>
      <xit:testcase name="EventHistoryReplay/17" success="true">
        <xit:bug type="bugzilla">https://bugs.freedesktop.org/show_bug.cgi?id=55477</xit:bug>
        <xit:fix type="git" repo="git://git.freedesktop.org/git/xorg/xserver">ce6b6529290f7d42717aad3fd8a83aaaaf8962de</xit:fix>
      </xit:testcase>
      <xit:testcase name="EventHistoryReplay/18" success="true">
        <xit:bug type="bugzilla">https://bugs.freedesktop.org/show_bug.cgi?id=55477</xit:bug>
        <xit:fix type="git" repo="git://git.freedesktop.org/git/xorg/xserver">ce6b6529290f7d42717aad3fd8a83aaaaf8962de</xit:fix>
      </xit:testcase>
      <xit:testcase name="EventHistoryReplay/19" success="true">
        <xit:bug type="bugzilla">https://bugs.freedesktop.org/show_bug.cgi?id=55477</xit:bug>
        <xit:fix type="git" repo="git://git.freedesktop.org/git/xorg/xserver">ce6b6529290f7d42717aad3fd8a83aaaaf8962de</xit:fix>
      </xit:testcase>
      <xit:testcase name="EventHistoryReplay/2" success="true">
        <xit:bug type="bugzilla">https://bugs.freedesktop.org/show_bug.cgi?id=55477</xit:bug>
        <xit:fix type="git" repo="git://git.freedesktop.org/git/xorg/xserver">ce6b6529290f7d42717aad3fd8a83aaaaf8962de</xit:fix>
      </xit:testcase>
      <xit:testcase name="EventHistoryReplay/3" success="true">
        <xit:bug type="bugzilla">https://bugs.freedesktop.org/show_bug.cgi?id=55477</xit:bug>
        <xit:fix type="git" repo="git://git.freedesktop.org/git/xorg/xserver">ce6b6529290f7d42717aad3fd8a83aaaaf8962de</xit:fix>
      </xit:testcase>
      <xit:testcase name="EventHistoryReplay/4" success="true">
        <xit:bug type="bugzilla">https://bugs.freedesktop.org/show_bug.cgi?id=55477</xit:bug>
        <xit:fix type="git" repo="git://git.freedesktop.org/git/xorg/xserver">ce6b6529290f7d42717aad3fd8a83aaaaf8962de</xit:fix>
      </xit:testcase>
      <xit:testcase name="EventHistoryReplay/5" success="true">
        <xit:bug type="bugzilla">https://bugs.freedesktop.org/show_bug.cgi?id=55477</xit:bug>
        <xit:fix type="git" repo="git://git.freedesktop.org/git/xorg/xserver">ce6b6529290f7d42717aad3fd8a83aaaaf8962de</xit:fix>
      </xit:testcase>
      <xit:testcase name="EventHistoryReplay/6" success="true">
        <xit:bug type="bugzilla">https://bugs.freedesktop.org/show_bug.cgi?id=55477</xit:bug>
        <xit:fix type="git" repo="git://git.freedesktop.org/git/xorg/xserver">ce6b6529290f7d42717aad3fd8a83aaaaf8962de</xit:fix>
      </xit:testcase>
      <xit:testcase name="EventHistoryReplay/7" success="true">
        <xit:bug type="bugzilla">https://bugs.freedesktop.org/show_bug.cgi?id=55477</xit:bug>
        <xit:fix type="git" repo="git://git.freedesktop.org/git/xorg/xserver">ce6b6529290f7d42717aad3fd8a83aaaaf8962de</xit:fix>
      </xit:testcase>
      <xit:testcase name="EventHistoryReplay/8" success="true">
        <xit:bug type="bugzilla">https://bugs.freedesktop.org/show_bug.cgi?id=55477</xit:bug>
        <xit:fix type="git" repo="git://git.freedesktop.org/git/xorg/xserver">ce6b6529290f7d42717aad3fd8a83aaaaf8962de</xit:fix>
      </xit:testcase>
      <xit:testcase name="EventHistoryReplay/9" success="true">
        <xit:bug type="bugzilla">https://bugs.freedesktop.org/show_bug.cgi?id=55477</xit:bug>
        <xit:fix type="git" repo="git://git.freedesktop.org/git/xorg/xserver">ce6b6529290f7d42717aad3fd8a83aaaaf8962de</xit:fix>
      </xit:testcase>
    </xit:testsuite>
    <xit:testsuite name="TouchGrabTestMultipleModes">
      <xit:testcase name="ActiveAndPassiveGrab/0" success="true">
        <xit:bug type="bugzilla">https://bugs.freedesktop.org/show_bug.cgi?id=55738</xit:bug>
        <xit:fix type="git" repo="git://git.freedesktop.org/git/xorg/xserver">676447190190d8546165e21be242cf16dd69f5ae</xit:fix>
      </xit:testcase>
      <xit:testcase name="ActiveAndPassiveGrab/1" success="true">
        <xit:bug type="bugzilla">https://bugs.freedesktop.org/show_bug.cgi?id=55738</xit:bug>
        <xit:fix type="git" repo="git://git.freedesktop.org/git/xorg/xserver">676447190190d8546165e21be242cf16dd69f5ae</xit:fix>
      </xit:testcase>
    </xit:testsuite>
    <xit:testsuite name="TouchGrabTestMultipleTaps">
      <xit:testcase name="PassiveGrabPointerEmulationMultipleTouchesFastSuccession/0" success="true"/>
      <xit:testcase name="PassiveGrabPointerEmulationMultipleTouchesFastSuccession/1" success="true"/>
      <xit:testcase name="PassiveGrabPointerEmulationMultipleTouchesFastSuccession/2" success="true"/>
      <xit:testcase name="PassiveGrabPointerEmulationMultipleTouchesFastSuccession/3" success="true"/>
      <xit:testcase name="PassiveGrabPointerEmulationMultipleTouchesFastSuccession/4" success="true"/>
      <xit:testcase name="PassiveGrabPointerEmulationMultipleTouchesFastSuccession/5" success="true">
        <xit:fix type="git" repo="git://git.freedesktop.org/git/xorg/xserver">00def5144557cfe8bf535f926212a8e084dc7cf6</xit:fix>
        <xit:fix type="git" repo="git://git.freedesktop.org/git/xorg/xserver">146f48c2934fc85ec095496da5c8f0102bc7f5b5</xit:fix>
        <xit:fix type="git" repo="git://git.freedesktop.org/git/xorg/xserver">bc1f90a615018c05994fae3e678dd2341256cd82</xit:fix>
        <xit:fix type="git" repo="git://git.freedesktop.org/git/xorg/xserver">ece8157a59751b3ed492fb2e1eb8d5f20221e195</xit:fix>
      </xit:testcase>
      <xit:testcase name="PassiveGrabPointerEmulationMultipleTouchesFastSuccession/6" success="true">
        <xit:fix type="git" repo="git://git.freedesktop.org/git/xorg/xserver">00def5144557cfe8bf535f926212a8e084dc7cf6</xit:fix>
        <xit:fix type="git" repo="git://git.freedesktop.org/git/xorg/xserver">146f48c2934fc85ec095496da5c8f0102bc7f5b5</xit:fix>
        <xit:fix type="git" repo="git://git.freedesktop.org/git/xorg/xserver">bc1f90a615018c05994fae3e678dd2341256cd82</xit:fix>
        <xit:fix type="git" repo="git://git.freedesktop.org/git/xorg/xserver">ece8157a59751b3ed492fb2e1eb8d5f20221e195</xit:fix>
      </xit:testcase>
      <xit:testcase name="PassiveGrabPointerEmulationMultipleTouchesFastSuccession/7" success="true">
        <xit:fix type="git" repo="git://git.freedesktop.org/git/xorg/xserver">00def5144557cfe8bf535f926212a8e084dc7cf6</xit:fix>
        <xit:fix type="git" repo="git://git.freedesktop.org/git/xorg/xserver">146f48c2934fc85ec095496da5c8f0102bc7f5b5</xit:fix>
        <xit:fix type="git" repo="git://git.freedesktop.org/git/xorg/xserver">bc1f90a615018c05994fae3e678dd2341256cd82</xit:fix>
        <xit:fix type="git" repo="git://git.freedesktop.org/git/xorg/xserver">ece8157a59751b3ed492fb2e1eb8d5f20221e195</xit:fix>
      </xit:testcase>
      <xit:testcase name="PassiveGrabPointerEmulationMultipleTouchesFastSuccession/8" success="true">
        <xit:fix type="git" repo="git://git.freedesktop.org/git/xorg/xserver">00def5144557cfe8bf535f926212a8e084dc7cf6</xit:fix>
        <xit:fix type="git" repo="git://git.freedesktop.org/git/xorg/xserver">146f48c2934fc85ec095496da5c8f0102bc7f5b5</xit:fix>
        <xit:fix type="git" repo="git://git.freedesktop.org/git/xorg/xserver">bc1f90a615018c05994fae3e678dd2341256cd82</xit:fix>
        <xit:fix type="git" repo="git://git.freedesktop.org/git/xorg/xserver">ece8157a59751b3ed492fb2e1eb8d5f20221e195</xit:fix>
      </xit:testcase>
      <xit:testcase name="PassiveGrabPointerEmulationMultipleTouchesFastSuccession/9" success="true">
        <xit:fix type="git" repo="git://git.freedesktop.org/git/xorg/xserver">00def5144557cfe8bf535f926212a8e084dc7cf6</xit:fix>
        <xit:fix type="git" repo="git://git.freedesktop.org/git/xorg/xserver">146f48c2934fc85ec095496da5c8f0102bc7f5b5</xit:fix>
        <xit:fix type="git" repo="git://git.freedesktop.org/git/xorg/xserver">bc1f90a615018c05994fae3e678dd2341256cd82</xit:fix>
        <xit:fix type="git" repo="git://git.freedesktop.org/git/xorg/xserver">ece8157a59751b3ed492fb2e1eb8d5f20221e195</xit:fix>
      </xit:testcase>
      <xit:testcase name="PassiveGrabPointerRelease/0" success="false"/>
      <xit:testcase name="PassiveGrabPointerRelease/1" success="false"/>
      <xit:testcase name="PassiveGrabPointerRelease/2" success="false"/>
      <xit:testcase name="PassiveGrabPointerRelease/3" success="false"/>
      <xit:testcase name="PassiveGrabPointerRelease/4" success="false"/>
      <xit:testcase name="PassiveGrabPointerRelease/5" success="false"/>
      <xit:testcase name="PassiveGrabPointerRelease/6" success="false"/>
      <xit:testcase name="PassiveGrabPointerRelease/7" success="false"/>
      <xit:testcase name="PassiveGrabPointerRelease/8" success="false"/>
      <xit:testcase name="PassiveGrabPointerRelease/9" success="false"/>
    </xit:testsuite>
    <xit:testsuite name="TouchOwnershipTest">
      <xit:testcase name="ActiveGrabOwnershipAcceptTouch" success="true"/>
      <xit:testcase name="ActiveGrabOwnershipRejectTouch" success="true"/>
      <xit:testcase name="ActiveGrabOwnershipUngrabDevice" success="true">
        <xit:fix type="git" repo="git://git.freedesktop.org/git/xorg/xserver">00def5144557cfe8bf535f926212a8e084dc7cf6</xit:fix>
      </xit:testcase>
      <xit:testcase name="ActivePointerGrabForWholeTouch" success="true">
        <xit:fix type="git" repo="git://git.freedesktop.org/git/xorg/xserver">00def5144557cfe8bf535f926212a8e084dc7cf6</xit:fix>
      </xit:testcase>
      <xit:testcase name="ActivePointerUngrabDuringTouch" success="true"/>
      <xit:testcase name="NoOwnershipAfterAcceptTouch" success="true"/>
      <xit:testcase name="OwnershipAfterRejectTouch" success="true"/>
    </xit:testsuite>
    <xit:testsuite name="TouchTest">
      <xit:testcase name="JumpingCursorOnTransformationMatrix" success="true">
        <xit:bug type="bugzilla">https://bugs.freedesktop.org/show_bug.cgi?id=49347</xit:bug>
        <xit:fix type="git" repo="git://git.freedesktop.org/git/xorg/xserver">3b9f1c701787965246638c1a6fd99fb2b6078114</xit:fix>
      </xit:testcase>
      <xit:testcase name="TouchEventsButtonState" success="true"/>
    </xit:testsuite>
    <xit:testsuite name="TouchTestXI2Version">
      <xit:testcase name="EmulatedButton1MotionMaskOnTouch/0" success="true"/>
      <xit:testcase name="EmulatedButton1MotionMaskOnTouch/1" success="true"/>
      <xit:testcase name="EmulatedButton1MotionMaskOnTouch/2" success="true"/>
      <xit:testcase name="EmulatedButton1MotionMaskOnTouch/3" success="true"/>
      <xit:testcase name="EmulatedButtonMaskOnTouchBeginEndCore/0" success="false"/>
      <xit:testcase name="EmulatedButtonMaskOnTouchBeginEndCore/1" success="false"/>
      <xit:testcase name="EmulatedButtonMaskOnTouchBeginEndCore/2" success="false"/>
      <xit:testcase name="EmulatedButtonMaskOnTouchBeginEndCore/3" success="false"/>
      <xit:testcase name="EmulatedButtonMaskOnTouchBeginEndXI2/0" success="true"/>
      <xit:testcase name="EmulatedButtonMaskOnTouchBeginEndXI2/1" success="true"/>
      <xit:testcase name="EmulatedButtonMaskOnTouchBeginEndXI2/2" success="true"/>
      <xit:testcase name="EmulatedButtonMaskOnTouchBeginEndXI2/3" success="true"/>
      <xit:testcase name="XIQueryPointerTouchscreen/0" success="true"/>
      <xit:testcase name="XIQueryPointerTouchscreen/1" success="true"/>
      <xit:testcase name="XIQueryPointerTouchscreen/2" success="true"/>
      <xit:testcase name="XIQueryPointerTouchscreen/3" success="true"/>
      <xit:testcase name="XITouchscreenPointerEmulation/0" success="true"/>
      <xit:testcase name="XITouchscreenPointerEmulation/1" success="true"/>
      <xit:testcase name="XITouchscreenPointerEmulation/2" success="true"/>
      <xit:testcase name="XITouchscreenPointerEmulation/3" success="true"/>
    </xit:testsuite>
    <xit:testsuite name="XIGrabButtonTest">
      <xit:testcase name="GrabWindowTest" success="true"/>
    </xit:testsuite>
    <xit:testsuite name="XISelectEventsTouchTest">
      <xit:testcase name="TouchSelectionConflicts/0" success="true">
        <xit:bug type="bugzilla">https://bugs.freedesktop.org/show_bug.cgi?id=57301</xit:bug>
      </xit:testcase>
      <xit:testcase name="TouchSelectionConflicts/1" success="true">
        <xit:bug type="bugzilla">https://bugs.freedesktop.org/show_bug.cgi?id=57301</xit:bug>
        <xit:fix type="git" repo="git://git.freedesktop.org/git/xorg/xserver">39f19b3f3b8c9b714e70e339dfb0083ff629ab2a</xit:fix>
      </xit:testcase>
      <xit:testcase name="TouchSelectionConflicts/2" success="true">
        <xit:bug type="bugzilla">https://bugs.freedesktop.org/show_bug.cgi?id=57301</xit:bug>
        <xit:fix type="git" repo="git://git.freedesktop.org/git/xorg/xserver">39f19b3f3b8c9b714e70e339dfb0083ff629ab2a</xit:fix>
      </xit:testcase>
      <xit:testcase name="TouchSelectionConflicts/3" success="true">
        <xit:bug type="bugzilla">https://bugs.freedesktop.org/show_bug.cgi?id=57301</xit:bug>
      </xit:testcase>
      <xit:testcase name="TouchSelectionConflicts/4" success="true">
        <xit:bug type="bugzilla">https://bugs.freedesktop.org/show_bug.cgi?id=57301</xit:bug>
      </xit:testcase>
      <xit:testcase name="TouchSelectionConflicts/5" success="true">
        <xit:bug type="bugzilla">https://bugs.freedesktop.org/show_bug.cgi?id=57301</xit:bug>
        <xit:fix type="git" repo="git://git.freedesktop.org/git/xorg/xserver">39f19b3f3b8c9b714e70e339dfb0083ff629ab2a</xit:fix>
      </xit:testcase>
      <xit:testcase name="TouchSelectionConflicts/6" success="true">
        <xit:bug type="bugzilla">https://bugs.freedesktop.org/show_bug.cgi?id=57301</xit:bug>
      </xit:testcase>
      <xit:testcase name="TouchSelectionConflicts/7" success="true">
        <xit:bug type="bugzilla">https://bugs.freedesktop.org/show_bug.cgi?id=57301</xit:bug>
      </xit:testcase>
      <xit:testcase name="TouchSelectionConflicts/8" success="true">
        <xit:bug type="bugzilla">https://bugs.freedesktop.org/show_bug.cgi?id=57301</xit:bug>
      </xit:testcase>
    </xit:testsuite>
    <xit:testsuite name="XTest">
      <xit:testcase name="DisabledDevicesCtl" success="true">
        <xit:bug type="bugzilla">https://bugs.freedesktop.org/show_bug.cgi?id=56380</xit:bug>
        <xit:fix type="git" repo="git://git.freedesktop.org/git/xorg/xserver">aad65415bff12c6860c19beac42e4165e598a40f</xit:fix>
      </xit:testcase>
      <xit:testcase name="DisabledDevicesProperty" success="true">
        <xit:bug type="bugzilla">https://bugs.freedesktop.org/show_bug.cgi?id=56380</xit:bug>
        <xit:fix type="git" repo="git://git.freedesktop.org/git/xorg/xserver">aad65415bff12c6860c19beac42e4165e598a40f</xit:fix>
      </xit:testcase>
    </xit:testsuite>
    <xit:testsuite name="XTestPhysicalDeviceTest">
      <xit:testcase name="ReleaseXTestOnPhysicalRelease" success="true">
        <xit:bug type="bugzilla">http://bugs.freedesktop.org/28808</xit:bug>
        <xit:fix type="git" repo="git://git.freedesktop.org/git/xorg/xserver">14327858391ebe929b806efb53ad79e789361883</xit:fix>
        <xit:fix type="git" repo="git://git.freedesktop.org/git/xorg/xserver">c4fee9d2ecd6fdd4c05b04c9f02b23f10f2938b8</xit:fix>
      </xit:testcase>
    </xit:testsuite>
    <xit:testsuite name="XineramaTest">
      <xit:testcase name="ScreenCrossing/0" success="true"/>
      <xit:testcase name="ScreenCrossing/1" success="true"/>
      <xit:testcase name="ScreenCrossingButtons/0" success="true"/>
      <xit:testcase name="ScreenCrossingButtons/1" success="true"/>
    </xit:testsuite>
    <xit:testsuite name="ZaphodTest">
      <xit:testcase name="ScreenCrossing/0" success="true">
        <xit:bug type="bugzilla">https://bugs.freedesktop.org/show_bug.cgi?id=54654</xit:bug>
        <xit:fix type="git" repo="git://git.freedesktop.org/git/xorg/xserver">e7cd5cce740e653000fb1192b600268dcf77dde2</xit:fix>
      </xit:testcase>
      <xit:testcase name="ScreenCrossing/1" success="true">
        <xit:bug type="bugzilla">https://bugs.freedesktop.org/show_bug.cgi?id=54654</xit:bug>
        <xit:fix type="git" repo="git://git.freedesktop.org/git/xorg/xserver">e7cd5cce740e653000fb1192b600268dcf77dde2</xit:fix>
      </xit:testcase>
      <xit:testcase name="ScreenCrossingButtons/0" success="true"/>
      <xit:testcase name="ScreenCrossingButtons/1" success="true"/>
    </xit:testsuite>
    <xit:testsuite name="ZaphodTouchDeviceChangeTest">
      <xit:testcase name="NoCursorJumpsOnTouchToPointerSwitch" success="true">
        <xit:bug type="bugzilla">https://bugs.freedesktop.org/show_bug.cgi?id=49347</xit:bug>
        <xit:fix type="git" repo="git://git.freedesktop.org/git/xorg/xserver">3b9f1c701787965246638c1a6fd99fb2b6078114</xit:fix>
      </xit:testcase>
    </xit:testsuite>
  </xit:registry>
</xit:registries>

